{
    "Filename": "/usr/include/x86_64-linux-gnu/qt6/QtWidgets/qwidgetaction.h",
    "Typedefs": [
        {
            "Alias": "__int128_t",
            "UnderlyingType": {
                "ParameterName": "",
                "ParameterType": "__int128",
                "Const": false,
                "Pointer": false,
                "PointerCount": 0,
                "ByRef": false,
                "Optional": false,
                "UniquePtr": false,
                "IsFunctionPointer": false,
                "IsStdFunction": false,
                "IsStdOptional": false,
                "FunctionPointer": null,
                "QtCppOriginalType": null,
                "BecomesConstInVersion": null
            }
        },
        {
            "Alias": "__uint128_t",
            "UnderlyingType": {
                "ParameterName": "",
                "ParameterType": "unsigned __int128",
                "Const": false,
                "Pointer": false,
                "PointerCount": 0,
                "ByRef": false,
                "Optional": false,
                "UniquePtr": false,
                "IsFunctionPointer": false,
                "IsStdFunction": false,
                "IsStdOptional": false,
                "FunctionPointer": null,
                "QtCppOriginalType": null,
                "BecomesConstInVersion": null
            }
        },
        {
            "Alias": "__NSConstantString",
            "UnderlyingType": {
                "ParameterName": "",
                "ParameterType": "__NSConstantString_tag",
                "Const": false,
                "Pointer": false,
                "PointerCount": 0,
                "ByRef": false,
                "Optional": false,
                "UniquePtr": false,
                "IsFunctionPointer": false,
                "IsStdFunction": false,
                "IsStdOptional": false,
                "FunctionPointer": null,
                "QtCppOriginalType": null,
                "BecomesConstInVersion": null
            }
        },
        {
            "Alias": "__builtin_ms_va_list",
            "UnderlyingType": {
                "ParameterName": "",
                "ParameterType": "char",
                "Const": false,
                "Pointer": true,
                "PointerCount": 1,
                "ByRef": false,
                "Optional": false,
                "UniquePtr": false,
                "IsFunctionPointer": false,
                "IsStdFunction": false,
                "IsStdOptional": false,
                "FunctionPointer": null,
                "QtCppOriginalType": null,
                "BecomesConstInVersion": null
            }
        },
        {
            "Alias": "__builtin_va_list",
            "UnderlyingType": {
                "ParameterName": "",
                "ParameterType": "__va_list_tag[1]",
                "Const": false,
                "Pointer": false,
                "PointerCount": 0,
                "ByRef": false,
                "Optional": false,
                "UniquePtr": false,
                "IsFunctionPointer": false,
                "IsStdFunction": false,
                "IsStdOptional": false,
                "FunctionPointer": null,
                "QtCppOriginalType": null,
                "BecomesConstInVersion": null
            }
        }
    ],
    "Enums": null,
    "Classes": [
        {
            "ClassName": "QWidgetAction",
            "Abstract": false,
            "Ctors": [
                {
                    "MethodName": "",
                    "OverrideMethodName": "",
                    "ReturnType": {
                        "ParameterName": "",
                        "ParameterType": "void",
                        "Const": false,
                        "Pointer": false,
                        "PointerCount": 0,
                        "ByRef": false,
                        "Optional": false,
                        "UniquePtr": false,
                        "IsFunctionPointer": false,
                        "IsStdFunction": false,
                        "IsStdOptional": false,
                        "FunctionPointer": null,
                        "QtCppOriginalType": null,
                        "BecomesConstInVersion": null
                    },
                    "Parameters": [
                        {
                            "ParameterName": "parent",
                            "ParameterType": "QObject",
                            "Const": false,
                            "Pointer": true,
                            "PointerCount": 1,
                            "ByRef": false,
                            "Optional": false,
                            "UniquePtr": false,
                            "IsFunctionPointer": false,
                            "IsStdFunction": false,
                            "IsStdOptional": false,
                            "FunctionPointer": null,
                            "QtCppOriginalType": null,
                            "BecomesConstInVersion": null
                        }
                    ],
                    "IsStatic": true,
                    "IsMoveCtor": false,
                    "IsSignal": false,
                    "IsConst": false,
                    "IsVariable": false,
                    "IsPrivate": false,
                    "IsVirtual": false,
                    "IsPureVirtual": false,
                    "IsProtected": false,
                    "IsFinal": false,
                    "HiddenParams": null,
                    "InheritedFrom": "",
                    "InheritedInClass": "",
                    "VariableFieldName": "",
                    "FossOnly": false,
                    "LinuxOnly": false,
                    "BecomesNonConstInVersion": null,
                    "HasStdFunctionPointerParam": false
                }
            ],
            "DirectInherits": [
                "QAction"
            ],
            "IncludedClasses": null,
            "Methods": [
                {
                    "MethodName": "metaObject",
                    "OverrideMethodName": "",
                    "ReturnType": {
                        "ParameterName": "",
                        "ParameterType": "QMetaObject",
                        "Const": true,
                        "Pointer": true,
                        "PointerCount": 1,
                        "ByRef": false,
                        "Optional": false,
                        "UniquePtr": false,
                        "IsFunctionPointer": false,
                        "IsStdFunction": false,
                        "IsStdOptional": false,
                        "FunctionPointer": null,
                        "QtCppOriginalType": null,
                        "BecomesConstInVersion": null
                    },
                    "Parameters": [],
                    "IsStatic": false,
                    "IsMoveCtor": false,
                    "IsSignal": false,
                    "IsConst": true,
                    "IsVariable": false,
                    "IsPrivate": false,
                    "IsVirtual": true,
                    "IsPureVirtual": false,
                    "IsProtected": false,
                    "IsFinal": false,
                    "HiddenParams": null,
                    "InheritedFrom": "",
                    "InheritedInClass": "",
                    "VariableFieldName": "",
                    "FossOnly": false,
                    "LinuxOnly": false,
                    "BecomesNonConstInVersion": null,
                    "HasStdFunctionPointerParam": false
                },
                {
                    "MethodName": "qt_metacast",
                    "OverrideMethodName": "",
                    "ReturnType": {
                        "ParameterName": "",
                        "ParameterType": "void",
                        "Const": false,
                        "Pointer": true,
                        "PointerCount": 1,
                        "ByRef": false,
                        "Optional": false,
                        "UniquePtr": false,
                        "IsFunctionPointer": false,
                        "IsStdFunction": false,
                        "IsStdOptional": false,
                        "FunctionPointer": null,
                        "QtCppOriginalType": null,
                        "BecomesConstInVersion": null
                    },
                    "Parameters": [
                        {
                            "ParameterName": "param1",
                            "ParameterType": "char",
                            "Const": true,
                            "Pointer": true,
                            "PointerCount": 1,
                            "ByRef": false,
                            "Optional": false,
                            "UniquePtr": false,
                            "IsFunctionPointer": false,
                            "IsStdFunction": false,
                            "IsStdOptional": false,
                            "FunctionPointer": null,
                            "QtCppOriginalType": null,
                            "BecomesConstInVersion": null
                        }
                    ],
                    "IsStatic": false,
                    "IsMoveCtor": false,
                    "IsSignal": false,
                    "IsConst": false,
                    "IsVariable": false,
                    "IsPrivate": false,
                    "IsVirtual": true,
                    "IsPureVirtual": false,
                    "IsProtected": false,
                    "IsFinal": false,
                    "HiddenParams": null,
                    "InheritedFrom": "",
                    "InheritedInClass": "",
                    "VariableFieldName": "",
                    "FossOnly": false,
                    "LinuxOnly": false,
                    "BecomesNonConstInVersion": null,
                    "HasStdFunctionPointerParam": false
                },
                {
                    "MethodName": "qt_metacall",
                    "OverrideMethodName": "",
                    "ReturnType": {
                        "ParameterName": "",
                        "ParameterType": "int",
                        "Const": false,
                        "Pointer": false,
                        "PointerCount": 0,
                        "ByRef": false,
                        "Optional": false,
                        "UniquePtr": false,
                        "IsFunctionPointer": false,
                        "IsStdFunction": false,
                        "IsStdOptional": false,
                        "FunctionPointer": null,
                        "QtCppOriginalType": null,
                        "BecomesConstInVersion": null
                    },
                    "Parameters": [
                        {
                            "ParameterName": "param1",
                            "ParameterType": "QMetaObject::Call",
                            "Const": false,
                            "Pointer": false,
                            "PointerCount": 0,
                            "ByRef": false,
                            "Optional": false,
                            "UniquePtr": false,
                            "IsFunctionPointer": false,
                            "IsStdFunction": false,
                            "IsStdOptional": false,
                            "FunctionPointer": null,
                            "QtCppOriginalType": null,
                            "BecomesConstInVersion": null
                        },
                        {
                            "ParameterName": "param2",
                            "ParameterType": "int",
                            "Const": false,
                            "Pointer": false,
                            "PointerCount": 0,
                            "ByRef": false,
                            "Optional": false,
                            "UniquePtr": false,
                            "IsFunctionPointer": false,
                            "IsStdFunction": false,
                            "IsStdOptional": false,
                            "FunctionPointer": null,
                            "QtCppOriginalType": null,
                            "BecomesConstInVersion": null
                        },
                        {
                            "ParameterName": "param3",
                            "ParameterType": "void",
                            "Const": false,
                            "Pointer": true,
                            "PointerCount": 2,
                            "ByRef": false,
                            "Optional": false,
                            "UniquePtr": false,
                            "IsFunctionPointer": false,
                            "IsStdFunction": false,
                            "IsStdOptional": false,
                            "FunctionPointer": null,
                            "QtCppOriginalType": null,
                            "BecomesConstInVersion": null
                        }
                    ],
                    "IsStatic": false,
                    "IsMoveCtor": false,
                    "IsSignal": false,
                    "IsConst": false,
                    "IsVariable": false,
                    "IsPrivate": false,
                    "IsVirtual": true,
                    "IsPureVirtual": false,
                    "IsProtected": false,
                    "IsFinal": false,
                    "HiddenParams": null,
                    "InheritedFrom": "",
                    "InheritedInClass": "",
                    "VariableFieldName": "",
                    "FossOnly": false,
                    "LinuxOnly": false,
                    "BecomesNonConstInVersion": null,
                    "HasStdFunctionPointerParam": false
                },
                {
                    "MethodName": "tr",
                    "OverrideMethodName": "",
                    "ReturnType": {
                        "ParameterName": "",
                        "ParameterType": "QString",
                        "Const": false,
                        "Pointer": false,
                        "PointerCount": 0,
                        "ByRef": false,
                        "Optional": false,
                        "UniquePtr": false,
                        "IsFunctionPointer": false,
                        "IsStdFunction": false,
                        "IsStdOptional": false,
                        "FunctionPointer": null,
                        "QtCppOriginalType": null,
                        "BecomesConstInVersion": null
                    },
                    "Parameters": [
                        {
                            "ParameterName": "s",
                            "ParameterType": "char",
                            "Const": true,
                            "Pointer": true,
                            "PointerCount": 1,
                            "ByRef": false,
                            "Optional": false,
                            "UniquePtr": false,
                            "IsFunctionPointer": false,
                            "IsStdFunction": false,
                            "IsStdOptional": false,
                            "FunctionPointer": null,
                            "QtCppOriginalType": null,
                            "BecomesConstInVersion": null
                        }
                    ],
                    "IsStatic": true,
                    "IsMoveCtor": false,
                    "IsSignal": false,
                    "IsConst": false,
                    "IsVariable": false,
                    "IsPrivate": false,
                    "IsVirtual": false,
                    "IsPureVirtual": false,
                    "IsProtected": false,
                    "IsFinal": false,
                    "HiddenParams": [
                        {
                            "ParameterName": "c",
                            "ParameterType": "char",
                            "Const": true,
                            "Pointer": true,
                            "PointerCount": 1,
                            "ByRef": false,
                            "Optional": true,
                            "UniquePtr": false,
                            "IsFunctionPointer": false,
                            "IsStdFunction": false,
                            "IsStdOptional": false,
                            "FunctionPointer": null,
                            "QtCppOriginalType": null,
                            "BecomesConstInVersion": null
                        },
                        {
                            "ParameterName": "n",
                            "ParameterType": "int",
                            "Const": false,
                            "Pointer": false,
                            "PointerCount": 0,
                            "ByRef": false,
                            "Optional": true,
                            "UniquePtr": false,
                            "IsFunctionPointer": false,
                            "IsStdFunction": false,
                            "IsStdOptional": false,
                            "FunctionPointer": null,
                            "QtCppOriginalType": null,
                            "BecomesConstInVersion": null
                        }
                    ],
                    "InheritedFrom": "",
                    "InheritedInClass": "",
                    "VariableFieldName": "",
                    "FossOnly": false,
                    "LinuxOnly": false,
                    "BecomesNonConstInVersion": null,
                    "HasStdFunctionPointerParam": false
                },
                {
                    "MethodName": "setDefaultWidget",
                    "OverrideMethodName": "",
                    "ReturnType": {
                        "ParameterName": "",
                        "ParameterType": "void",
                        "Const": false,
                        "Pointer": false,
                        "PointerCount": 0,
                        "ByRef": false,
                        "Optional": false,
                        "UniquePtr": false,
                        "IsFunctionPointer": false,
                        "IsStdFunction": false,
                        "IsStdOptional": false,
                        "FunctionPointer": null,
                        "QtCppOriginalType": null,
                        "BecomesConstInVersion": null
                    },
                    "Parameters": [
                        {
                            "ParameterName": "w",
                            "ParameterType": "QWidget",
                            "Const": false,
                            "Pointer": true,
                            "PointerCount": 1,
                            "ByRef": false,
                            "Optional": false,
                            "UniquePtr": false,
                            "IsFunctionPointer": false,
                            "IsStdFunction": false,
                            "IsStdOptional": false,
                            "FunctionPointer": null,
                            "QtCppOriginalType": null,
                            "BecomesConstInVersion": null
                        }
                    ],
                    "IsStatic": false,
                    "IsMoveCtor": false,
                    "IsSignal": false,
                    "IsConst": false,
                    "IsVariable": false,
                    "IsPrivate": false,
                    "IsVirtual": false,
                    "IsPureVirtual": false,
                    "IsProtected": false,
                    "IsFinal": false,
                    "HiddenParams": null,
                    "InheritedFrom": "",
                    "InheritedInClass": "",
                    "VariableFieldName": "",
                    "FossOnly": false,
                    "LinuxOnly": false,
                    "BecomesNonConstInVersion": null,
                    "HasStdFunctionPointerParam": false
                },
                {
                    "MethodName": "defaultWidget",
                    "OverrideMethodName": "",
                    "ReturnType": {
                        "ParameterName": "",
                        "ParameterType": "QWidget",
                        "Const": false,
                        "Pointer": true,
                        "PointerCount": 1,
                        "ByRef": false,
                        "Optional": false,
                        "UniquePtr": false,
                        "IsFunctionPointer": false,
                        "IsStdFunction": false,
                        "IsStdOptional": false,
                        "FunctionPointer": null,
                        "QtCppOriginalType": null,
                        "BecomesConstInVersion": null
                    },
                    "Parameters": [],
                    "IsStatic": false,
                    "IsMoveCtor": false,
                    "IsSignal": false,
                    "IsConst": true,
                    "IsVariable": false,
                    "IsPrivate": false,
                    "IsVirtual": false,
                    "IsPureVirtual": false,
                    "IsProtected": false,
                    "IsFinal": false,
                    "HiddenParams": null,
                    "InheritedFrom": "",
                    "InheritedInClass": "",
                    "VariableFieldName": "",
                    "FossOnly": false,
                    "LinuxOnly": false,
                    "BecomesNonConstInVersion": null,
                    "HasStdFunctionPointerParam": false
                },
                {
                    "MethodName": "requestWidget",
                    "OverrideMethodName": "",
                    "ReturnType": {
                        "ParameterName": "",
                        "ParameterType": "QWidget",
                        "Const": false,
                        "Pointer": true,
                        "PointerCount": 1,
                        "ByRef": false,
                        "Optional": false,
                        "UniquePtr": false,
                        "IsFunctionPointer": false,
                        "IsStdFunction": false,
                        "IsStdOptional": false,
                        "FunctionPointer": null,
                        "QtCppOriginalType": null,
                        "BecomesConstInVersion": null
                    },
                    "Parameters": [
                        {
                            "ParameterName": "parent",
                            "ParameterType": "QWidget",
                            "Const": false,
                            "Pointer": true,
                            "PointerCount": 1,
                            "ByRef": false,
                            "Optional": false,
                            "UniquePtr": false,
                            "IsFunctionPointer": false,
                            "IsStdFunction": false,
                            "IsStdOptional": false,
                            "FunctionPointer": null,
                            "QtCppOriginalType": null,
                            "BecomesConstInVersion": null
                        }
                    ],
                    "IsStatic": false,
                    "IsMoveCtor": false,
                    "IsSignal": false,
                    "IsConst": false,
                    "IsVariable": false,
                    "IsPrivate": false,
                    "IsVirtual": false,
                    "IsPureVirtual": false,
                    "IsProtected": false,
                    "IsFinal": false,
                    "HiddenParams": null,
                    "InheritedFrom": "",
                    "InheritedInClass": "",
                    "VariableFieldName": "",
                    "FossOnly": false,
                    "LinuxOnly": false,
                    "BecomesNonConstInVersion": null,
                    "HasStdFunctionPointerParam": false
                },
                {
                    "MethodName": "releaseWidget",
                    "OverrideMethodName": "",
                    "ReturnType": {
                        "ParameterName": "",
                        "ParameterType": "void",
                        "Const": false,
                        "Pointer": false,
                        "PointerCount": 0,
                        "ByRef": false,
                        "Optional": false,
                        "UniquePtr": false,
                        "IsFunctionPointer": false,
                        "IsStdFunction": false,
                        "IsStdOptional": false,
                        "FunctionPointer": null,
                        "QtCppOriginalType": null,
                        "BecomesConstInVersion": null
                    },
                    "Parameters": [
                        {
                            "ParameterName": "widget",
                            "ParameterType": "QWidget",
                            "Const": false,
                            "Pointer": true,
                            "PointerCount": 1,
                            "ByRef": false,
                            "Optional": false,
                            "UniquePtr": false,
                            "IsFunctionPointer": false,
                            "IsStdFunction": false,
                            "IsStdOptional": false,
                            "FunctionPointer": null,
                            "QtCppOriginalType": null,
                            "BecomesConstInVersion": null
                        }
                    ],
                    "IsStatic": false,
                    "IsMoveCtor": false,
                    "IsSignal": false,
                    "IsConst": false,
                    "IsVariable": false,
                    "IsPrivate": false,
                    "IsVirtual": false,
                    "IsPureVirtual": false,
                    "IsProtected": false,
                    "IsFinal": false,
                    "HiddenParams": null,
                    "InheritedFrom": "",
                    "InheritedInClass": "",
                    "VariableFieldName": "",
                    "FossOnly": false,
                    "LinuxOnly": false,
                    "BecomesNonConstInVersion": null,
                    "HasStdFunctionPointerParam": false
                },
                {
                    "MethodName": "event",
                    "OverrideMethodName": "",
                    "ReturnType": {
                        "ParameterName": "",
                        "ParameterType": "bool",
                        "Const": false,
                        "Pointer": false,
                        "PointerCount": 0,
                        "ByRef": false,
                        "Optional": false,
                        "UniquePtr": false,
                        "IsFunctionPointer": false,
                        "IsStdFunction": false,
                        "IsStdOptional": false,
                        "FunctionPointer": null,
                        "QtCppOriginalType": null,
                        "BecomesConstInVersion": null
                    },
                    "Parameters": [
                        {
                            "ParameterName": "param1",
                            "ParameterType": "QEvent",
                            "Const": false,
                            "Pointer": true,
                            "PointerCount": 1,
                            "ByRef": false,
                            "Optional": false,
                            "UniquePtr": false,
                            "IsFunctionPointer": false,
                            "IsStdFunction": false,
                            "IsStdOptional": false,
                            "FunctionPointer": null,
                            "QtCppOriginalType": null,
                            "BecomesConstInVersion": null
                        }
                    ],
                    "IsStatic": false,
                    "IsMoveCtor": false,
                    "IsSignal": false,
                    "IsConst": false,
                    "IsVariable": false,
                    "IsPrivate": false,
                    "IsVirtual": true,
                    "IsPureVirtual": false,
                    "IsProtected": true,
                    "IsFinal": false,
                    "HiddenParams": null,
                    "InheritedFrom": "",
                    "InheritedInClass": "",
                    "VariableFieldName": "",
                    "FossOnly": false,
                    "LinuxOnly": false,
                    "BecomesNonConstInVersion": null,
                    "HasStdFunctionPointerParam": false
                },
                {
                    "MethodName": "eventFilter",
                    "OverrideMethodName": "",
                    "ReturnType": {
                        "ParameterName": "",
                        "ParameterType": "bool",
                        "Const": false,
                        "Pointer": false,
                        "PointerCount": 0,
                        "ByRef": false,
                        "Optional": false,
                        "UniquePtr": false,
                        "IsFunctionPointer": false,
                        "IsStdFunction": false,
                        "IsStdOptional": false,
                        "FunctionPointer": null,
                        "QtCppOriginalType": null,
                        "BecomesConstInVersion": null
                    },
                    "Parameters": [
                        {
                            "ParameterName": "param1",
                            "ParameterType": "QObject",
                            "Const": false,
                            "Pointer": true,
                            "PointerCount": 1,
                            "ByRef": false,
                            "Optional": false,
                            "UniquePtr": false,
                            "IsFunctionPointer": false,
                            "IsStdFunction": false,
                            "IsStdOptional": false,
                            "FunctionPointer": null,
                            "QtCppOriginalType": null,
                            "BecomesConstInVersion": null
                        },
                        {
                            "ParameterName": "param2",
                            "ParameterType": "QEvent",
                            "Const": false,
                            "Pointer": true,
                            "PointerCount": 1,
                            "ByRef": false,
                            "Optional": false,
                            "UniquePtr": false,
                            "IsFunctionPointer": false,
                            "IsStdFunction": false,
                            "IsStdOptional": false,
                            "FunctionPointer": null,
                            "QtCppOriginalType": null,
                            "BecomesConstInVersion": null
                        }
                    ],
                    "IsStatic": false,
                    "IsMoveCtor": false,
                    "IsSignal": false,
                    "IsConst": false,
                    "IsVariable": false,
                    "IsPrivate": false,
                    "IsVirtual": true,
                    "IsPureVirtual": false,
                    "IsProtected": true,
                    "IsFinal": false,
                    "HiddenParams": null,
                    "InheritedFrom": "",
                    "InheritedInClass": "",
                    "VariableFieldName": "",
                    "FossOnly": false,
                    "LinuxOnly": false,
                    "BecomesNonConstInVersion": null,
                    "HasStdFunctionPointerParam": false
                },
                {
                    "MethodName": "createWidget",
                    "OverrideMethodName": "",
                    "ReturnType": {
                        "ParameterName": "",
                        "ParameterType": "QWidget",
                        "Const": false,
                        "Pointer": true,
                        "PointerCount": 1,
                        "ByRef": false,
                        "Optional": false,
                        "UniquePtr": false,
                        "IsFunctionPointer": false,
                        "IsStdFunction": false,
                        "IsStdOptional": false,
                        "FunctionPointer": null,
                        "QtCppOriginalType": null,
                        "BecomesConstInVersion": null
                    },
                    "Parameters": [
                        {
                            "ParameterName": "parent",
                            "ParameterType": "QWidget",
                            "Const": false,
                            "Pointer": true,
                            "PointerCount": 1,
                            "ByRef": false,
                            "Optional": false,
                            "UniquePtr": false,
                            "IsFunctionPointer": false,
                            "IsStdFunction": false,
                            "IsStdOptional": false,
                            "FunctionPointer": null,
                            "QtCppOriginalType": null,
                            "BecomesConstInVersion": null
                        }
                    ],
                    "IsStatic": false,
                    "IsMoveCtor": false,
                    "IsSignal": false,
                    "IsConst": false,
                    "IsVariable": false,
                    "IsPrivate": false,
                    "IsVirtual": true,
                    "IsPureVirtual": false,
                    "IsProtected": true,
                    "IsFinal": false,
                    "HiddenParams": null,
                    "InheritedFrom": "",
                    "InheritedInClass": "",
                    "VariableFieldName": "",
                    "FossOnly": false,
                    "LinuxOnly": false,
                    "BecomesNonConstInVersion": null,
                    "HasStdFunctionPointerParam": false
                },
                {
                    "MethodName": "deleteWidget",
                    "OverrideMethodName": "",
                    "ReturnType": {
                        "ParameterName": "",
                        "ParameterType": "void",
                        "Const": false,
                        "Pointer": false,
                        "PointerCount": 0,
                        "ByRef": false,
                        "Optional": false,
                        "UniquePtr": false,
                        "IsFunctionPointer": false,
                        "IsStdFunction": false,
                        "IsStdOptional": false,
                        "FunctionPointer": null,
                        "QtCppOriginalType": null,
                        "BecomesConstInVersion": null
                    },
                    "Parameters": [
                        {
                            "ParameterName": "widget",
                            "ParameterType": "QWidget",
                            "Const": false,
                            "Pointer": true,
                            "PointerCount": 1,
                            "ByRef": false,
                            "Optional": false,
                            "UniquePtr": false,
                            "IsFunctionPointer": false,
                            "IsStdFunction": false,
                            "IsStdOptional": false,
                            "FunctionPointer": null,
                            "QtCppOriginalType": null,
                            "BecomesConstInVersion": null
                        }
                    ],
                    "IsStatic": false,
                    "IsMoveCtor": false,
                    "IsSignal": false,
                    "IsConst": false,
                    "IsVariable": false,
                    "IsPrivate": false,
                    "IsVirtual": true,
                    "IsPureVirtual": false,
                    "IsProtected": true,
                    "IsFinal": false,
                    "HiddenParams": null,
                    "InheritedFrom": "",
                    "InheritedInClass": "",
                    "VariableFieldName": "",
                    "FossOnly": false,
                    "LinuxOnly": false,
                    "BecomesNonConstInVersion": null,
                    "HasStdFunctionPointerParam": false
                },
                {
                    "MethodName": "createdWidgets",
                    "OverrideMethodName": "",
                    "ReturnType": {
                        "ParameterName": "",
                        "ParameterType": "QList\u003cQWidget*\u003e",
                        "Const": false,
                        "Pointer": false,
                        "PointerCount": 0,
                        "ByRef": false,
                        "Optional": false,
                        "UniquePtr": false,
                        "IsFunctionPointer": false,
                        "IsStdFunction": false,
                        "IsStdOptional": false,
                        "FunctionPointer": null,
                        "QtCppOriginalType": {
                            "ParameterName": "",
                            "ParameterType": "QList\u003cQWidget*\u003e",
                            "Const": false,
                            "Pointer": false,
                            "PointerCount": 0,
                            "ByRef": false,
                            "Optional": false,
                            "UniquePtr": false,
                            "IsFunctionPointer": false,
                            "IsStdFunction": false,
                            "IsStdOptional": false,
                            "FunctionPointer": null,
                            "QtCppOriginalType": null,
                            "BecomesConstInVersion": null
                        },
                        "BecomesConstInVersion": null
                    },
                    "Parameters": [],
                    "IsStatic": false,
                    "IsMoveCtor": false,
                    "IsSignal": false,
                    "IsConst": true,
                    "IsVariable": false,
                    "IsPrivate": false,
                    "IsVirtual": false,
                    "IsPureVirtual": false,
                    "IsProtected": true,
                    "IsFinal": false,
                    "HiddenParams": null,
                    "InheritedFrom": "",
                    "InheritedInClass": "",
                    "VariableFieldName": "",
                    "FossOnly": false,
                    "LinuxOnly": false,
                    "BecomesNonConstInVersion": null,
                    "HasStdFunctionPointerParam": false
                },
                {
                    "MethodName": "tr2",
                    "OverrideMethodName": "tr",
                    "ReturnType": {
                        "ParameterName": "",
                        "ParameterType": "QString",
                        "Const": false,
                        "Pointer": false,
                        "PointerCount": 0,
                        "ByRef": false,
                        "Optional": false,
                        "UniquePtr": false,
                        "IsFunctionPointer": false,
                        "IsStdFunction": false,
                        "IsStdOptional": false,
                        "FunctionPointer": null,
                        "QtCppOriginalType": null,
                        "BecomesConstInVersion": null
                    },
                    "Parameters": [
                        {
                            "ParameterName": "s",
                            "ParameterType": "char",
                            "Const": true,
                            "Pointer": true,
                            "PointerCount": 1,
                            "ByRef": false,
                            "Optional": false,
                            "UniquePtr": false,
                            "IsFunctionPointer": false,
                            "IsStdFunction": false,
                            "IsStdOptional": false,
                            "FunctionPointer": null,
                            "QtCppOriginalType": null,
                            "BecomesConstInVersion": null
                        },
                        {
                            "ParameterName": "c",
                            "ParameterType": "char",
                            "Const": true,
                            "Pointer": true,
                            "PointerCount": 1,
                            "ByRef": false,
                            "Optional": true,
                            "UniquePtr": false,
                            "IsFunctionPointer": false,
                            "IsStdFunction": false,
                            "IsStdOptional": false,
                            "FunctionPointer": null,
                            "QtCppOriginalType": null,
                            "BecomesConstInVersion": null
                        }
                    ],
                    "IsStatic": true,
                    "IsMoveCtor": false,
                    "IsSignal": false,
                    "IsConst": false,
                    "IsVariable": false,
                    "IsPrivate": false,
                    "IsVirtual": false,
                    "IsPureVirtual": false,
                    "IsProtected": false,
                    "IsFinal": false,
                    "HiddenParams": [
                        {
                            "ParameterName": "n",
                            "ParameterType": "int",
                            "Const": false,
                            "Pointer": false,
                            "PointerCount": 0,
                            "ByRef": false,
                            "Optional": true,
                            "UniquePtr": false,
                            "IsFunctionPointer": false,
                            "IsStdFunction": false,
                            "IsStdOptional": false,
                            "FunctionPointer": null,
                            "QtCppOriginalType": null,
                            "BecomesConstInVersion": null
                        }
                    ],
                    "InheritedFrom": "",
                    "InheritedInClass": "",
                    "VariableFieldName": "",
                    "FossOnly": false,
                    "LinuxOnly": false,
                    "BecomesNonConstInVersion": null,
                    "HasStdFunctionPointerParam": false
                },
                {
                    "MethodName": "tr3",
                    "OverrideMethodName": "tr",
                    "ReturnType": {
                        "ParameterName": "",
                        "ParameterType": "QString",
                        "Const": false,
                        "Pointer": false,
                        "PointerCount": 0,
                        "ByRef": false,
                        "Optional": false,
                        "UniquePtr": false,
                        "IsFunctionPointer": false,
                        "IsStdFunction": false,
                        "IsStdOptional": false,
                        "FunctionPointer": null,
                        "QtCppOriginalType": null,
                        "BecomesConstInVersion": null
                    },
                    "Parameters": [
                        {
                            "ParameterName": "s",
                            "ParameterType": "char",
                            "Const": true,
                            "Pointer": true,
                            "PointerCount": 1,
                            "ByRef": false,
                            "Optional": false,
                            "UniquePtr": false,
                            "IsFunctionPointer": false,
                            "IsStdFunction": false,
                            "IsStdOptional": false,
                            "FunctionPointer": null,
                            "QtCppOriginalType": null,
                            "BecomesConstInVersion": null
                        },
                        {
                            "ParameterName": "c",
                            "ParameterType": "char",
                            "Const": true,
                            "Pointer": true,
                            "PointerCount": 1,
                            "ByRef": false,
                            "Optional": true,
                            "UniquePtr": false,
                            "IsFunctionPointer": false,
                            "IsStdFunction": false,
                            "IsStdOptional": false,
                            "FunctionPointer": null,
                            "QtCppOriginalType": null,
                            "BecomesConstInVersion": null
                        },
                        {
                            "ParameterName": "n",
                            "ParameterType": "int",
                            "Const": false,
                            "Pointer": false,
                            "PointerCount": 0,
                            "ByRef": false,
                            "Optional": true,
                            "UniquePtr": false,
                            "IsFunctionPointer": false,
                            "IsStdFunction": false,
                            "IsStdOptional": false,
                            "FunctionPointer": null,
                            "QtCppOriginalType": null,
                            "BecomesConstInVersion": null
                        }
                    ],
                    "IsStatic": true,
                    "IsMoveCtor": false,
                    "IsSignal": false,
                    "IsConst": false,
                    "IsVariable": false,
                    "IsPrivate": false,
                    "IsVirtual": false,
                    "IsPureVirtual": false,
                    "IsProtected": false,
                    "IsFinal": false,
                    "HiddenParams": [],
                    "InheritedFrom": "",
                    "InheritedInClass": "",
                    "VariableFieldName": "",
                    "FossOnly": false,
                    "LinuxOnly": false,
                    "BecomesNonConstInVersion": null,
                    "HasStdFunctionPointerParam": false
                }
            ],
            "Props": null,
            "CanDelete": true,
            "HasTrivialCopyAssign": false,
            "HasTrivialMoveAssign": false,
            "ChildTypedefs": null,
            "ChildClassdefs": null,
            "ChildEnums": null,
            "PrivateMethods": [
                "qt_static_metacall",
                "d_func",
                "d_func",
                "operator="
            ],
            "PrivateSignals": null,
            "IsPolymorphic": false
        }
    ]
}